phenogcb/__init__.py
phenogcb-0.1.0.dist-info/METADATA
phenogcb-0.1.0.dist-info/RECORD
phenogcb-0.1.0.dist-info/WHEEL
phenogcb-0.1.0.dist-info/top_level.txt
