Metadata-Version: 2.1
Name: phenogcb
Version: 0.1.0
Summary: Pheno GCB
Home-page: https://catalyseur.ca
Author: Pierre Proulx
Author-email: pierre.proulx@usherbrooke.ca
License: UNKNOWN
Platform: UNKNOWN
Classifier: Programming Language :: Python :: 3
Classifier: License :: OSI Approved :: MIT License
Classifier: Operating System :: OS Independent
